fcoder/__about__.py
fcoder/__init__.py
fcoder/client.py
fcoder/content.py
fcoder/error.py
fcoder/message.py
fcoder-0.0.1b1.dist-info/METADATA
fcoder-0.0.1b1.dist-info/WHEEL
fcoder-0.0.1b1.dist-info/RECORD
